streamlit_iiif_viewer/__init__.py
streamlit_iiif_viewer/frontend/dist/index.html
streamlit_iiif_viewer/frontend/dist/assets/index-BpzIZ9KN.css
streamlit_iiif_viewer/frontend/dist/assets/index-CKnG94y6.js
streamlit_iiif_viewer/frontend/dist/assets/index-CKnG94y6.js.map
streamlit_iiif_viewer/frontend/dist/assets/tify-D_JVwBUj.js
streamlit_iiif_viewer/frontend/dist/assets/tify-D_JVwBUj.js.map
streamlit_iiif_viewer/frontend/dist/mirador/mirador.min.js
streamlit_iiif_viewer/frontend/dist/translations/bg.json
streamlit_iiif_viewer/frontend/dist/translations/de.json
streamlit_iiif_viewer/frontend/dist/translations/eo.json
streamlit_iiif_viewer/frontend/dist/translations/fr.json
streamlit_iiif_viewer/frontend/dist/translations/hr.json
streamlit_iiif_viewer/frontend/dist/translations/it.json
streamlit_iiif_viewer/frontend/dist/translations/ja.json
streamlit_iiif_viewer/frontend/dist/translations/nl.json
streamlit_iiif_viewer/frontend/dist/translations/pl.json
streamlit_iiif_viewer/frontend/dist/translations/sq.json
streamlit_iiif_viewer/frontend/dist/translations/tr.json
streamlit_iiif_viewer/frontend/dist/translations/zh.json
streamlit_iiif_viewer-0.0.3.dist-info/licenses/LICENSE
streamlit_iiif_viewer-0.0.3.dist-info/METADATA
streamlit_iiif_viewer-0.0.3.dist-info/WHEEL
streamlit_iiif_viewer-0.0.3.dist-info/top_level.txt
streamlit_iiif_viewer-0.0.3.dist-info/RECORD
