Metadata-Version: 2.4
Name: streamlit-iiif-viewer
Version: 0.0.3
Summary: A Streamlit component for show IIIF viewers.
Home-page: 
Author: Lucas Terriel
Author-email: contact@lterriel.com
License: MIT
Keywords: streamlit-component streamlit iiif viewer
Requires-Python: >=3.9
License-File: LICENSE
Requires-Dist: streamlit>=1.34.0
Dynamic: author
Dynamic: author-email
Dynamic: description
Dynamic: description-content-type
Dynamic: keywords
Dynamic: license
Dynamic: license-file
Dynamic: requires-dist
Dynamic: requires-python
Dynamic: summary
